deepspeed_mii-0.3.3.dist-info/licenses/LICENSE
mii/__init__.py
mii/api.py
mii/config.py
mii/constants.py
mii/errors.py
mii/logging.py
mii/utils.py
mii/version.py
mii/aml_related/__init__.py
mii/aml_related/templates.py
mii/aml_related/utils.py
mii/backend/__init__.py
mii/backend/client.py
mii/backend/server.py
mii/batching/__init__.py
mii/batching/constants.py
mii/batching/data_classes.py
mii/batching/postprocess.py
mii/batching/ragged_batching.py
mii/batching/utils.py
mii/batching/generation/__init__.py
mii/batching/generation/logit_processors.py
mii/batching/generation/samplers.py
mii/batching/generation/stop_criterion.py
mii/entrypoints/__init__.py
mii/entrypoints/api_server.py
mii/entrypoints/data_models.py
mii/entrypoints/openai_api_server.py
mii/grpc_related/__init__.py
mii/grpc_related/modelresponse_server.py
mii/grpc_related/restful_gateway.py
mii/grpc_related/task_methods.py
mii/grpc_related/proto/__init__.py
mii/grpc_related/proto/modelresponse_pb2.py
mii/grpc_related/proto/modelresponse_pb2_grpc.py
mii/launch/__init__.py
mii/launch/multi_gpu_server.py
mii/legacy/__init__.py
mii/legacy/client.py
mii/legacy/config.py
mii/legacy/constants.py
mii/legacy/deployment.py
mii/legacy/logging.py
mii/legacy/method_table.py
mii/legacy/server.py
mii/legacy/terminate.py
mii/legacy/utils.py
mii/legacy/aml_related/__init__.py
mii/legacy/aml_related/templates.py
mii/legacy/aml_related/utils.py
mii/legacy/grpc_related/__init__.py
mii/legacy/grpc_related/modelresponse_server.py
mii/legacy/grpc_related/restful_gateway.py
mii/legacy/grpc_related/proto/__init__.py
mii/legacy/grpc_related/proto/legacymodelresponse_pb2.py
mii/legacy/grpc_related/proto/legacymodelresponse_pb2_grpc.py
mii/legacy/launch/__init__.py
mii/legacy/launch/multi_gpu_server.py
mii/legacy/models/__init__.py
mii/legacy/models/load_models.py
mii/legacy/models/utils.py
mii/legacy/models/providers/__init__.py
mii/legacy/models/providers/diffusers.py
mii/legacy/models/providers/eleutherai.py
mii/legacy/models/providers/huggingface.py
deepspeed_mii-0.3.3.dist-info/METADATA
deepspeed_mii-0.3.3.dist-info/WHEEL
deepspeed_mii-0.3.3.dist-info/top_level.txt
deepspeed_mii-0.3.3.dist-info/RECORD
