Metadata-Version: 2.4
Name: deepspeed-mii
Version: 0.3.3
Summary: deepspeed mii
Home-page: http://deepspeed.ai
Author: DeepSpeed Team
Author-email: deepspeed-mii@microsoft.com
Project-URL: Documentation, https://github.com/deepspeedai/DeepSpeed-MII
Project-URL: Source, https://github.com/deepspeedai/DeepSpeed-MII
Classifier: Programming Language :: Python :: 3.8
Classifier: Programming Language :: Python :: 3.9
Classifier: Programming Language :: Python :: 3.10
Classifier: Programming Language :: Python :: 3.11
Classifier: Programming Language :: Python :: 3.12
License-File: LICENSE
Requires-Dist: accelerate
Requires-Dist: asyncio
Requires-Dist: deepspeed>=0.15.0
Requires-Dist: deepspeed-kernels
Requires-Dist: fastapi
Requires-Dist: fastchat
Requires-Dist: Flask-RESTful
Requires-Dist: grpcio
Requires-Dist: grpcio-tools
Requires-Dist: Pillow
Requires-Dist: pydantic>=2.0.0
Requires-Dist: pyzmq
Requires-Dist: safetensors
Requires-Dist: shortuuid
Requires-Dist: torch
Requires-Dist: transformers
Requires-Dist: ujson
Requires-Dist: Werkzeug
Provides-Extra: dev
Requires-Dist: clang-format==18.1.3; extra == "dev"
Requires-Dist: einops; extra == "dev"
Requires-Dist: pre-commit>=2.20.0; extra == "dev"
Requires-Dist: pytest; extra == "dev"
Requires-Dist: pytest-forked; extra == "dev"
Requires-Dist: sentencepiece; extra == "dev"
Requires-Dist: tiktoken; extra == "dev"
Requires-Dist: transformers-stream-generator; extra == "dev"
Dynamic: author
Dynamic: author-email
Dynamic: classifier
Dynamic: description
Dynamic: description-content-type
Dynamic: home-page
Dynamic: license-file
Dynamic: project-url
Dynamic: provides-extra
Dynamic: requires-dist
Dynamic: summary
